ukr_numbers/__init__.py
ukr_numbers/__main__.py
ukr_numbers/data_structures.py
ukr_numbers/nums.py
ukr_numbers-0.1.4.dist-info/LICENSE
ukr_numbers-0.1.4.dist-info/METADATA
ukr_numbers-0.1.4.dist-info/WHEEL
ukr_numbers-0.1.4.dist-info/entry_points.txt
ukr_numbers-0.1.4.dist-info/RECORD
