Metadata-Version: 2.1
Name: ukr-numbers
Version: 0.1.4
Summary: Transform integers to correctly inflected Ukrainian words (3 → третьої)
Author: Serhii Hamotskyi
Author-email: serhii@serhii.net
Requires-Python: >=3.10,<4.0
Classifier: Programming Language :: Python :: 3
Classifier: Programming Language :: Python :: 3.10
Classifier: Programming Language :: Python :: 3.11
Classifier: Programming Language :: Python :: 3.12
Classifier: Programming Language :: Python :: 3.13
Requires-Dist: num2words (>=0.5.13,<0.6.0)
Requires-Dist: pymorphy3 (>=2.0.2,<3.0.0)
Requires-Dist: pymorphy3-dicts-uk (>=2.4.1.1.1663094765,<3.0.0.0.0)
